README.rst
setup.py
telegram/__init__.py
telegram/bottle.py
telegram/http.py
telegram/requestdump.py
telegram/telegram.py
telegram_bot.egg-info/PKG-INFO
telegram_bot.egg-info/SOURCES.txt
telegram_bot.egg-info/dependency_links.txt
telegram_bot.egg-info/top_level.txt