Metadata-Version: 1.1
Name: telegram-bot
Version: 0.1
Summary: telegram-bot help creating telegram bots in python.
Home-page: https://github.com/gravmatt/telegram-bot
Author: Rene Tanczos
Author-email: gravmatt@gmail.com
License: MIT
Platform: all
Classifier: Intended Audience :: Developers
Classifier: License :: OSI Approved :: MIT License
Classifier: Programming Language :: Python :: 2.5
Classifier: Programming Language :: Python :: 2.6
Classifier: Programming Language :: Python :: 2.7
Classifier: Intended Audience :: Developers
Classifier: Programming Language :: Python
